TIME_COUNTER/time_counter.v
// module counter(seconds, minutes,toggle,reset,clk_sec,clk_min,clk_hours);
module counter(seconds, minutes,toggle,reset,clk_sec,clk_min,clk_hours);


  input wire toggle; //Will stop counting unless
  input wire reset; //Will drive all counter to zero
  reg[1:0] toggleState = 1;//1 --> Count, 0 -->Not Count

  input wire clk_sec;   //SECONDS Clock singal T = 1seg, use falling edge detection
  input wire clk_min;   //MINUTES Clok signal  T = 1min, use falling edge detection
  input wire clk_hours; //HOURS Clok signal  T = 1hour, use falling edge detection


  parameter WIDTH = 8;

//Start counter in -1. GtkWave simulation counts falling edge at the beggining (Double check during synthesis required)
  output reg [WIDTH-1 : 0] seconds  = -1; 
  output reg [WIDTH-1 : 0] minutes  = -1;
  output reg [WIDTH-1 : 0] hours    = -1;


//SECONDS
//Detection of falling edge in clk_sec singal
  always @(negedge clk_sec)
  begin
    seconds <= seconds + 1;  //Asyn assing, increase 1 second
    if(seconds == 59)        //Avoid overflow and restart counter
      seconds <= 0;
  end

//MINUTES
//Detection of falling edge in clk_min singal
  always @(negedge clk_min)
  begin  
    minutes <= minutes + 1;   //Se hace la asignación instantanea,,
    if(minutes == 59)        //Avoid overflow and restart counter
      minutes <= 0;
  end

//HOURS
//Detection of falling edge in clk_min singal
  always @(negedge clk_hours)
  begin  
    hours <= hours + 1;   //Se hace la asignación instantanea,,
    if(hours == 99)        //Avoid overflow and restart counter
      hours <= 0;
  end

endmodule // counter

DEPRECATED MODULES/TIME_COUNTER/sec_clock.v
//Generador de clock con periodo T = 1 segundo. Debe contarse cada flanco de bajada
`timescale 1s / 100us //Cada tick en verilog va a durar 100uS. Además la minima unidad seran los 100 uS
module sec_clock_gen(output reg sec_clk);

parameter PERIOD = 1;
	 
	 //Genera la onda cuadrada
always
	begin: CLOCK_DRIVER //CLOCK_DRIVER es un tag que no es relevante
		sec_clk <= 1'b0;	//Se pone el clock en 0, es la bajada
		#(PERIOD*0.5); 	//Semiperiodo del clock
		sec_clk <= 1'b1;	//Subida del clock
		#(PERIOD*0.5);	//Segunda parte del periodo
	end
endmodule

TIME_COUNTER/min_clock.v
//Generador de clock con periodo T = 1 minuto. Debe contarse cada flanco de bajada
`timescale 100s / 1s //Cada tick en verilog va a durar 100uS. Además la minima unidad seran los 100 uS
module min_clock_gen(output reg min_clk);

parameter PERIOD = 1;
	 
	 //Genera la onda cuadrada
always
	begin: CLOCK_DRIVER //CLOCK_DRIVER es un tag que no es relevante
		min_clk <= 1'b0;	//Se pone el clock en 0, es la bajada
		#(PERIOD*0.3); 	//Semiperiodo del clock
		min_clk <= 1'b1;	//Subida del clock
		#(PERIOD*0.3);	//Segunda parte del periodo
	end
endmodule

DEPRECATED MODULES/CLK_HOURS/hours_clock.v
`timescale 100s / 1s //Cada tick en verilog va a durar 100uS. Además la minima unidad seran los 100 uS
module hours_clock_gen(hours_clk);

output reg hours_clk;

parameter PERIOD = 1;
	 
	 //Genera la onda cuadrada
always
	begin: CLOCK_DRIVER //CLOCK_DRIVER es un tag que no es relevante
		hours_clk <= 1'b0;	//Se pone el clock en 0, es la bajada
		#(PERIOD*18); 	//Semiperiodo del clock
		hours_clk <= 1'b1;	//Subida del clock
		#(PERIOD*18);	//Segunda parte del periodo
	end
endmodule

DEPRECATED MODULES/TIME_COUNTER/main.v
//TestBench of clock signals and counter module
module hello_world;

  // My signal definitions
  wire clk_sec;
  wire clk_min;
  wire clk_hours;

  wire reset;
  wire toggle;

  hours_clock_gen hours_clk_gen(clk_hours);
  min_clock_gen min_clk_gen(clk_min);
  sec_clock_gen sec_clk_gen(clk_sec);

  //reg reset = 0;

  wire[7:0] seconds;
  wire[7:0] minutes;
  wire[7:0] hours;

  //Estamos enviando un parametro
  counter my_counter(seconds, minutes, toggle, reset, clk_sec,clk_min,clk_hours);

  initial begin

    #10000;
    $finish;

  end
  
  // initial  begin
  //   $monitor(seconds);
  // end

  // Additional documentation on $dumpfile and $dumpvars: http://referencedesigner.com/tutorials/verilog/verilog_62.php
  // Setup to allow us to pass an output path for $dumpfile
  reg dummy;
  reg[8*64:0] dumpfile_path = "output.vcd";

  initial begin
    dummy = $value$plusargs("VCD_PATH=%s", dumpfile_path);
    $dumpfile(dumpfile_path);
    $dumpvars(0,hello_world);
  end

endmodule // End of Module hello_world

DEPRECATED MODULES/TIME_COUNTER/output.vcd
$date
	Mon Nov 19 15:50:41 2018
$end
$version
	Icarus Verilog
$end
$timescale
	100us
$end
$scope module hello_world $end
$var wire 1 ! reset $end
$var wire 1 " toggle $end
$var wire 8 # seconds [7:0] $end
$var wire 8 $ minutes [7:0] $end
$var wire 1 % clk_sec $end
$var wire 1 & clk_min $end
$var wire 1 ' clk_hours $end
$var reg 1 ( dummy $end
$var reg 513 ) dumpfile_path [512:0] $end
$scope module hours_clk_gen $end
$var reg 1 ' hours_clk $end
$scope begin CLOCK_DRIVER $end
$upscope $end
$upscope $end
$scope module min_clk_gen $end
$var reg 1 & min_clk $end
$scope begin CLOCK_DRIVER $end
$upscope $end
$upscope $end
$scope module my_counter $end
$var wire 1 ' clk_hours $end
$var wire 1 & clk_min $end
$var wire 1 ! reset $end
$var wire 1 " toggle $end
$var wire 1 % clk_sec $end
$var reg 8 * hours [7:0] $end
$var reg 8 + minutes [7:0] $end
$var reg 8 , seconds [7:0] $end
$var reg 2 - toggleState [1:0] $end
$upscope $end
$scope module sec_clk_gen $end
$var reg 1 % sec_clk $end
$scope begin CLOCK_DRIVER $end
$upscope $end
$upscope $end
$upscope $end
$enddefinitions $end
#0
$dumpvars
b1 -
b0 ,
b0 +
b0 *
b1101111011101010111010001110000011101010111010000101110011101100110001101100100 )
0(
0'
0&
0%
b0 $
b0 #
z"
z!
$end
#5000
1%
#10000
b1 #
b1 ,
0%
#15000
1%
#20000
b10 #
b10 ,
0%
#25000
1%
#30000
b11 #
b11 ,
0%
#35000
1%
#40000
b100 #
b100 ,
0%
#45000
1%
#50000
b101 #
b101 ,
0%
#55000
1%
#60000
b110 #
b110 ,
0%
#65000
1%
#70000
b111 #
b111 ,
0%
#75000
1%
#80000
b1000 #
b1000 ,
0%
#85000
1%
#90000
b1001 #
b1001 ,
0%
#95000
1%
#100000
b1010 #
b1010 ,
0%
#105000
1%
#110000
b1011 #
b1011 ,
0%
#115000
1%
#120000
b1100 #
b1100 ,
0%
#125000
1%
#130000
b1101 #
b1101 ,
0%
#135000
1%
#140000
b1110 #
b1110 ,
0%
#145000
1%
#150000
b1111 #
b1111 ,
0%
#155000
1%
#160000
b10000 #
b10000 ,
0%
#165000
1%
#170000
b10001 #
b10001 ,
0%
#175000
1%
#180000
b10010 #
b10010 ,
0%
#185000
1%
#190000
b10011 #
b10011 ,
0%
#195000
1%
#200000
b10100 #
b10100 ,
0%
#205000
1%
#210000
b10101 #
b10101 ,
0%
#215000
1%
#220000
b10110 #
b10110 ,
0%
#225000
1%
#230000
b10111 #
b10111 ,
0%
#235000
1%
#240000
b11000 #
b11000 ,
0%
#245000
1%
#250000
b11001 #
b11001 ,
0%
#255000
1%
#260000
b11010 #
b11010 ,
0%
#265000
1%
#270000
b11011 #
b11011 ,
0%
#275000
1%
#280000
b11100 #
b11100 ,
0%
#285000
1%
#290000
b11101 #
b11101 ,
0%
#295000
1%
#300000
b11110 #
b11110 ,
0%
1&
#305000
1%
#310000
b11111 #
b11111 ,
0%
#315000
1%
#320000
b100000 #
b100000 ,
0%
#325000
1%
#330000
b100001 #
b100001 ,
0%
#335000
1%
#340000
b100010 #
b100010 ,
0%
#345000
1%
#350000
b100011 #
b100011 ,
0%
#355000
1%
#360000
b100100 #
b100100 ,
0%
#365000
1%
#370000
b100101 #
b100101 ,
0%
#375000
1%
#380000
b100110 #
b100110 ,
0%
#385000
1%
#390000
b100111 #
b100111 ,
0%
#395000
1%
#400000
b101000 #
b101000 ,
0%
#405000
1%
#410000
b101001 #
b101001 ,
0%
#415000
1%
#420000
b101010 #
b101010 ,
0%
#425000
1%
#430000
b101011 #
b101011 ,
0%
#435000
1%
#440000
b101100 #
b101100 ,
0%
#445000
1%
#450000
b101101 #
b101101 ,
0%
#455000
1%
#460000
b101110 #
b101110 ,
0%
#465000
1%
#470000
b101111 #
b101111 ,
0%
#475000
1%
#480000
b110000 #
b110000 ,
0%
#485000
1%
#490000
b110001 #
b110001 ,
0%
#495000
1%
#500000
b110010 #
b110010 ,
0%
#505000
1%
#510000
b110011 #
b110011 ,
0%
#515000
1%
#520000
b110100 #
b110100 ,
0%
#525000
1%
#530000
b110101 #
b110101 ,
0%
#535000
1%
#540000
b110110 #
b110110 ,
0%
#545000
1%
#550000
b110111 #
b110111 ,
0%
#555000
1%
#560000
b111000 #
b111000 ,
0%
#565000
1%
#570000
b111001 #
b111001 ,
0%
#575000
1%
#580000
b111010 #
b111010 ,
0%
#585000
1%
#590000
b111011 #
b111011 ,
0%
#595000
1%
#600000
b0 #
b0 ,
b1 $
b1 +
0%
0&
#605000
1%
#610000
b1 #
b1 ,
0%
#615000
1%
#620000
b10 #
b10 ,
0%
#625000
1%
#630000
b11 #
b11 ,
0%
#635000
1%
#640000
b100 #
b100 ,
0%
#645000
1%
#650000
b101 #
b101 ,
0%
#655000
1%
#660000
b110 #
b110 ,
0%
#665000
1%
#670000
b111 #
b111 ,
0%
#675000
1%
#680000
b1000 #
b1000 ,
0%
#685000
1%
#690000
b1001 #
b1001 ,
0%
#695000
1%
#700000
b1010 #
b1010 ,
0%
#705000
1%
#710000
b1011 #
b1011 ,
0%
#715000
1%
#720000
b1100 #
b1100 ,
0%
#725000
1%
#730000
b1101 #
b1101 ,
0%
#735000
1%
#740000
b1110 #
b1110 ,
0%
#745000
1%
#750000
b1111 #
b1111 ,
0%
#755000
1%
#760000
b10000 #
b10000 ,
0%
#765000
1%
#770000
b10001 #
b10001 ,
0%
#775000
1%
#780000
b10010 #
b10010 ,
0%
#785000
1%
#790000
b10011 #
b10011 ,
0%
#795000
1%
#800000
b10100 #
b10100 ,
0%
#805000
1%
#810000
b10101 #
b10101 ,
0%
#815000
1%
#820000
b10110 #
b10110 ,
0%
#825000
1%
#830000
b10111 #
b10111 ,
0%
#835000
1%
#840000
b11000 #
b11000 ,
0%
#845000
1%
#850000
b11001 #
b11001 ,
0%
#855000
1%
#860000
b11010 #
b11010 ,
0%
#865000
1%
#870000
b11011 #
b11011 ,
0%
#875000
1%
#880000
b11100 #
b11100 ,
0%
#885000
1%
#890000
b11101 #
b11101 ,
0%
#895000
1%
#900000
b11110 #
b11110 ,
0%
1&
#905000
1%
#910000
b11111 #
b11111 ,
0%
#915000
1%
#920000
b100000 #
b100000 ,
0%
#925000
1%
#930000
b100001 #
b100001 ,
0%
#935000
1%
#940000
b100010 #
b100010 ,
0%
#945000
1%
#950000
b100011 #
b100011 ,
0%
#955000
1%
#960000
b100100 #
b100100 ,
0%
#965000
1%
#970000
b100101 #
b100101 ,
0%
#975000
1%
#980000
b100110 #
b100110 ,
0%
#985000
1%
#990000
b100111 #
b100111 ,
0%
#995000
1%
#1000000
b101000 #
b101000 ,
0%
#1005000
1%
#1010000
b101001 #
b101001 ,
0%
#1015000
1%
#1020000
b101010 #
b101010 ,
0%
#1025000
1%
#1030000
b101011 #
b101011 ,
0%
#1035000
1%
#1040000
b101100 #
b101100 ,
0%
#1045000
1%
#1050000
b101101 #
b101101 ,
0%
#1055000
1%
#1060000
b101110 #
b101110 ,
0%
#1065000
1%
#1070000
b101111 #
b101111 ,
0%
#1075000
1%
#1080000
b110000 #
b110000 ,
0%
#1085000
1%
#1090000
b110001 #
b110001 ,
0%
#1095000
1%
#1100000
b110010 #
b110010 ,
0%
#1105000
1%
#1110000
b110011 #
b110011 ,
0%
#1115000
1%
#1120000
b110100 #
b110100 ,
0%
#1125000
1%
#1130000
b110101 #
b110101 ,
0%
#1135000
1%
#1140000
b110110 #
b110110 ,
0%
#1145000
1%
#1150000
b110111 #
b110111 ,
0%
#1155000
1%
#1160000
b111000 #
b111000 ,
0%
#1165000
1%
#1170000
b111001 #
b111001 ,
0%
#1175000
1%
#1180000
b111010 #
b111010 ,
0%
#1185000
1%
#1190000
b111011 #
b111011 ,
0%
#1195000
1%
#1200000
b0 #
b0 ,
b10 $
b10 +
0%
0&
#1205000
1%
#1210000
b1 #
b1 ,
0%
#1215000
1%
#1220000
b10 #
b10 ,
0%
#1225000
1%
#1230000
b11 #
b11 ,
0%
#1235000
1%
#1240000
b100 #
b100 ,
0%
#1245000
1%
#1250000
b101 #
b101 ,
0%
#1255000
1%
#1260000
b110 #
b110 ,
0%
#1265000
1%
#1270000
b111 #
b111 ,
0%
#1275000
1%
#1280000
b1000 #
b1000 ,
0%
#1285000
1%
#1290000
b1001 #
b1001 ,
0%
#1295000
1%
#1300000
b1010 #
b1010 ,
0%
#1305000
1%
#1310000
b1011 #
b1011 ,
0%
#1315000
1%
#1320000
b1100 #
b1100 ,
0%
#1325000
1%
#1330000
b1101 #
b1101 ,
0%
#1335000
1%
#1340000
b1110 #
b1110 ,
0%
#1345000
1%
#1350000
b1111 #
b1111 ,
0%
#1355000
1%
#1360000
b10000 #
b10000 ,
0%
#1365000
1%
#1370000
b10001 #
b10001 ,
0%
#1375000
1%
#1380000
b10010 #
b10010 ,
0%
#1385000
1%
#1390000
b10011 #
b10011 ,
0%
#1395000
1%
#1400000
b10100 #
b10100 ,
0%
#1405000
1%
#1410000
b10101 #
b10101 ,
0%
#1415000
1%
#1420000
b10110 #
b10110 ,
0%
#1425000
1%
#1430000
b10111 #
b10111 ,
0%
#1435000
1%
#1440000
b11000 #
b11000 ,
0%
#1445000
1%
#1450000
b11001 #
b11001 ,
0%
#1455000
1%
#1460000
b11010 #
b11010 ,
0%
#1465000
1%
#1470000
b11011 #
b11011 ,
0%
#1475000
1%
#1480000
b11100 #
b11100 ,
0%
#1485000
1%
#1490000
b11101 #
b11101 ,
0%
#1495000
1%
#1500000
b11110 #
b11110 ,
0%
1&
#1505000
1%
#1510000
b11111 #
b11111 ,
0%
#1515000
1%
#1520000
b100000 #
b100000 ,
0%
#1525000
1%
#1530000
b100001 #
b100001 ,
0%
#1535000
1%
#1540000
b100010 #
b100010 ,
0%
#1545000
1%
#1550000
b100011 #
b100011 ,
0%
#1555000
1%
#1560000
b100100 #
b100100 ,
0%
#1565000
1%
#1570000
b100101 #
b100101 ,
0%
#1575000
1%
#1580000
b100110 #
b100110 ,
0%
#1585000
1%
#1590000
b100111 #
b100111 ,
0%
#1595000
1%
#1600000
b101000 #
b101000 ,
0%
#1605000
1%
#1610000
b101001 #
b101001 ,
0%
#1615000
1%
#1620000
b101010 #
b101010 ,
0%
#1625000
1%
#1630000
b101011 #
b101011 ,
0%
#1635000
1%
#1640000
b101100 #
b101100 ,
0%
#1645000
1%
#1650000
b101101 #
b101101 ,
0%
#1655000
1%
#1660000
b101110 #
b101110 ,
0%
#1665000
1%
#1670000
b101111 #
b101111 ,
0%
#1675000
1%
#1680000
b110000 #
b110000 ,
0%
#1685000
1%
#1690000
b110001 #
b110001 ,
0%
#1695000
1%
#1700000
b110010 #
b110010 ,
0%
#1705000
1%
#1710000
b110011 #
b110011 ,
0%
#1715000
1%
#1720000
b110100 #
b110100 ,
0%
#1725000
1%
#1730000
b110101 #
b110101 ,
0%
#1735000
1%
#1740000
b110110 #
b110110 ,
0%
#1745000
1%
#1750000
b110111 #
b110111 ,
0%
#1755000
1%
#1760000
b111000 #
b111000 ,
0%
#1765000
1%
#1770000
b111001 #
b111001 ,
0%
#1775000
1%
#1780000
b111010 #
b111010 ,
0%
#1785000
1%
#1790000
b111011 #
b111011 ,
0%
#1795000
1%
#1800000
b0 #
b0 ,
b11 $
b11 +
0%
0&
#1805000
1%
#1810000
b1 #
b1 ,
0%
#1815000
1%
#1820000
b10 #
b10 ,
0%
#1825000
1%
#1830000
b11 #
b11 ,
0%
#1835000
1%
#1840000
b100 #
b100 ,
0%
#1845000
1%
#1850000
b101 #
b101 ,
0%
#1855000
1%
#1860000
b110 #
b110 ,
0%
#1865000
1%
#1870000
b111 #
b111 ,
0%
#1875000
1%
#1880000
b1000 #
b1000 ,
0%
#1885000
1%
#1890000
b1001 #
b1001 ,
0%
#1895000
1%
#1900000
b1010 #
b1010 ,
0%
#1905000
1%
#1910000
b1011 #
b1011 ,
0%
#1915000
1%
#1920000
b1100 #
b1100 ,
0%
#1925000
1%
#1930000
b1101 #
b1101 ,
0%
#1935000
1%
#1940000
b1110 #
b1110 ,
0%
#1945000
1%
#1950000
b1111 #
b1111 ,
0%
#1955000
1%
#1960000
b10000 #
b10000 ,
0%
#1965000
1%
#1970000
b10001 #
b10001 ,
0%
#1975000
1%
#1980000
b10010 #
b10010 ,
0%
#1985000
1%
#1990000
b10011 #
b10011 ,
0%
#1995000
1%
#2000000
b10100 #
b10100 ,
0%
#2005000
1%
#2010000
b10101 #
b10101 ,
0%
#2015000
1%
#2020000
b10110 #
b10110 ,
0%
#2025000
1%
#2030000
b10111 #
b10111 ,
0%
#2035000
1%
#2040000
b11000 #
b11000 ,
0%
#2045000
1%
#2050000
b11001 #
b11001 ,
0%
#2055000
1%
#2060000
b11010 #
b11010 ,
0%
#2065000
1%
#2070000
b11011 #
b11011 ,
0%
#2075000
1%
#2080000
b11100 #
b11100 ,
0%
#2085000
1%
#2090000
b11101 #
b11101 ,
0%
#2095000
1%
#2100000
b11110 #
b11110 ,
0%
1&
#2105000
1%
#2110000
b11111 #
b11111 ,
0%
#2115000
1%
#2120000
b100000 #
b100000 ,
0%
#2125000
1%
#2130000
b100001 #
b100001 ,
0%
#2135000
1%
#2140000
b100010 #
b100010 ,
0%
#2145000
1%
#2150000
b100011 #
b100011 ,
0%
#2155000
1%
#2160000
b100100 #
b100100 ,
0%
#2165000
1%
#2170000
b100101 #
b100101 ,
0%
#2175000
1%
#2180000
b100110 #
b100110 ,
0%
#2185000
1%
#2190000
b100111 #
b100111 ,
0%
#2195000
1%
#2200000
b101000 #
b101000 ,
0%
#2205000
1%
#2210000
b101001 #
b101001 ,
0%
#2215000
1%
#2220000
b101010 #
b101010 ,
0%
#2225000
1%
#2230000
b101011 #
b101011 ,
0%
#2235000
1%
#2240000
b101100 #
b101100 ,
0%
#2245000
1%
#2250000
b101101 #
b101101 ,
0%
#2255000
1%
#2260000
b101110 #
b101110 ,
0%
#2265000
1%
#2270000
b101111 #
b101111 ,
0%
#2275000
1%
#2280000
b110000 #
b110000 ,
0%
#2285000
1%
#2290000
b110001 #
b110001 ,
0%
#2295000
1%
#2300000
b110010 #
b110010 ,
0%
#2305000
1%
#2310000
b110011 #
b110011 ,
0%
#2315000
1%
#2320000
b110100 #
b110100 ,
0%
#2325000
1%
#2330000
b110101 #
b110101 ,
0%
#2335000
1%
#2340000
b110110 #
b110110 ,
0%
#2345000
1%
#2350000
b110111 #
b110111 ,
0%
#2355000
1%
#2360000
b111000 #
b111000 ,
0%
#2365000
1%
#2370000
b111001 #
b111001 ,
0%
#2375000
1%
#2380000
b111010 #
b111010 ,
0%
#2385000
1%
#2390000
b111011 #
b111011 ,
0%
#2395000
1%
#2400000
b0 #
b0 ,
b100 $
b100 +
0%
0&
#2405000
1%
#2410000
b1 #
b1 ,
0%
#2415000
1%
#2420000
b10 #
b10 ,
0%
#2425000
1%
#2430000
b11 #
b11 ,
0%
#2435000
1%
#2440000
b100 #
b100 ,
0%
#2445000
1%
#2450000
b101 #
b101 ,
0%
#2455000
1%
#2460000
b110 #
b110 ,
0%
#2465000
1%
#2470000
b111 #
b111 ,
0%
#2475000
1%
#2480000
b1000 #
b1000 ,
0%
#2485000
1%
#2490000
b1001 #
b1001 ,
0%
#2495000
1%
#2500000
b1010 #
b1010 ,
0%
#2505000
1%
#2510000
b1011 #
b1011 ,
0%
#2515000
1%
#2520000
b1100 #
b1100 ,
0%
#2525000
1%
#2530000
b1101 #
b1101 ,
0%
#2535000
1%
#2540000
b1110 #
b1110 ,
0%
#2545000
1%
#2550000
b1111 #
b1111 ,
0%
#2555000
1%
#2560000
b10000 #
b10000 ,
0%
#2565000
1%
#2570000
b10001 #
b10001 ,
0%
#2575000
1%
#2580000
b10010 #
b10010 ,
0%
#2585000
1%
#2590000
b10011 #
b10011 ,
0%
#2595000
1%
#2600000
b10100 #
b10100 ,
0%
#2605000
1%
#2610000
b10101 #
b10101 ,
0%
#2615000
1%
#2620000
b10110 #
b10110 ,
0%
#2625000
1%
#2630000
b10111 #
b10111 ,
0%
#2635000
1%
#2640000
b11000 #
b11000 ,
0%
#2645000
1%
#2650000
b11001 #
b11001 ,
0%
#2655000
1%
#2660000
b11010 #
b11010 ,
0%
#2665000
1%
#2670000
b11011 #
b11011 ,
0%
#2675000
1%
#2680000
b11100 #
b11100 ,
0%
#2685000
1%
#2690000
b11101 #
b11101 ,
0%
#2695000
1%
#2700000
b11110 #
b11110 ,
0%
1&
#2705000
1%
#2710000
b11111 #
b11111 ,
0%
#2715000
1%
#2720000
b100000 #
b100000 ,
0%
#2725000
1%
#2730000
b100001 #
b100001 ,
0%
#2735000
1%
#2740000
b100010 #
b100010 ,
0%
#2745000
1%
#2750000
b100011 #
b100011 ,
0%
#2755000
1%
#2760000
b100100 #
b100100 ,
0%
#2765000
1%
#2770000
b100101 #
b100101 ,
0%
#2775000
1%
#2780000
b100110 #
b100110 ,
0%
#2785000
1%
#2790000
b100111 #
b100111 ,
0%
#2795000
1%
#2800000
b101000 #
b101000 ,
0%
#2805000
1%
#2810000
b101001 #
b101001 ,
0%
#2815000
1%
#2820000
b101010 #
b101010 ,
0%
#2825000
1%
#2830000
b101011 #
b101011 ,
0%
#2835000
1%
#2840000
b101100 #
b101100 ,
0%
#2845000
1%
#2850000
b101101 #
b101101 ,
0%
#2855000
1%
#2860000
b101110 #
b101110 ,
0%
#2865000
1%
#2870000
b101111 #
b101111 ,
0%
#2875000
1%
#2880000
b110000 #
b110000 ,
0%
#2885000
1%
#2890000
b110001 #
b110001 ,
0%
#2895000
1%
#2900000
b110010 #
b110010 ,
0%
#2905000
1%
#2910000
b110011 #
b110011 ,
0%
#2915000
1%
#2920000
b110100 #
b110100 ,
0%
#2925000
1%
#2930000
b110101 #
b110101 ,
0%
#2935000
1%
#2940000
b110110 #
b110110 ,
0%
#2945000
1%
#2950000
b110111 #
b110111 ,
0%
#2955000
1%
#2960000
b111000 #
b111000 ,
0%
#2965000
1%
#2970000
b111001 #
b111001 ,
0%
#2975000
1%
#2980000
b111010 #
b111010 ,
0%
#2985000
1%
#2990000
b111011 #
b111011 ,
0%
#2995000
1%
#3000000
b0 #
b0 ,
b101 $
b101 +
0%
0&
#3005000
1%
#3010000
b1 #
b1 ,
0%
#3015000
1%
#3020000
b10 #
b10 ,
0%
#3025000
1%
#3030000
b11 #
b11 ,
0%
#3035000
1%
#3040000
b100 #
b100 ,
0%
#3045000
1%
#3050000
b101 #
b101 ,
0%
#3055000
1%
#3060000
b110 #
b110 ,
0%
#3065000
1%
#3070000
b111 #
b111 ,
0%
#3075000
1%
#3080000
b1000 #
b1000 ,
0%
#3085000
1%
#3090000
b1001 #
b1001 ,
0%
#3095000
1%
#3100000
b1010 #
b1010 ,
0%
#3105000
1%
#3110000
b1011 #
b1011 ,
0%
#3115000
1%
#3120000
b1100 #
b1100 ,
0%
#3125000
1%
#3130000
b1101 #
b1101 ,
0%
#3135000
1%
#3140000
b1110 #
b1110 ,
0%
#3145000
1%
#3150000
b1111 #
b1111 ,
0%
#3155000
1%
#3160000
b10000 #
b10000 ,
0%
#3165000
1%
#3170000
b10001 #
b10001 ,
0%
#3175000
1%
#3180000
b10010 #
b10010 ,
0%
#3185000
1%
#3190000
b10011 #
b10011 ,
0%
#3195000
1%
#3200000
b10100 #
b10100 ,
0%
#3205000
1%
#3210000
b10101 #
b10101 ,
0%
#3215000
1%
#3220000
b10110 #
b10110 ,
0%
#3225000
1%
#3230000
b10111 #
b10111 ,
0%
#3235000
1%
#3240000
b11000 #
b11000 ,
0%
#3245000
1%
#3250000
b11001 #
b11001 ,
0%
#3255000
1%
#3260000
b11010 #
b11010 ,
0%
#3265000
1%
#3270000
b11011 #
b11011 ,
0%
#3275000
1%
#3280000
b11100 #
b11100 ,
0%
#3285000
1%
#3290000
b11101 #
b11101 ,
0%
#3295000
1%
#3300000
b11110 #
b11110 ,
0%
1&
#3305000
1%
#3310000
b11111 #
b11111 ,
0%
#3315000
1%
#3320000
b100000 #
b100000 ,
0%
#3325000
1%
#3330000
b100001 #
b100001 ,
0%
#3335000
1%
#3340000
b100010 #
b100010 ,
0%
#3345000
1%
#3350000
b100011 #
b100011 ,
0%
#3355000
1%
#3360000
b100100 #
b100100 ,
0%
#3365000
1%
#3370000
b100101 #
b100101 ,
0%
#3375000
1%
#3380000
b100110 #
b100110 ,
0%
#3385000
1%
#3390000
b100111 #
b100111 ,
0%
#3395000
1%
#3400000
b101000 #
b101000 ,
0%
#3405000
1%
#3410000
b101001 #
b101001 ,
0%
#3415000
1%
#3420000
b101010 #
b101010 ,
0%
#3425000
1%
#3430000
b101011 #
b101011 ,
0%
#3435000
1%
#3440000
b101100 #
b101100 ,
0%
#3445000
1%
#3450000
b101101 #
b101101 ,
0%
#3455000
1%
#3460000
b101110 #
b101110 ,
0%
#3465000
1%
#3470000
b101111 #
b101111 ,
0%
#3475000
1%
#3480000
b110000 #
b110000 ,
0%
#3485000
1%
#3490000
b110001 #
b110001 ,
0%
#3495000
1%
#3500000
b110010 #
b110010 ,
0%
#3505000
1%
#3510000
b110011 #
b110011 ,
0%
#3515000
1%
#3520000
b110100 #
b110100 ,
0%
#3525000
1%
#3530000
b110101 #
b110101 ,
0%
#3535000
1%
#3540000
b110110 #
b110110 ,
0%
#3545000
1%
#3550000
b110111 #
b110111 ,
0%
#3555000
1%
#3560000
b111000 #
b111000 ,
0%
#3565000
1%
#3570000
b111001 #
b111001 ,
0%
#3575000
1%
#3580000
b111010 #
b111010 ,
0%
#3585000
1%
#3590000
b111011 #
b111011 ,
0%
#3595000
1%
#3600000
b0 #
b0 ,
b110 $
b110 +
0%
0&
#3605000
1%
#3610000
b1 #
b1 ,
0%
#3615000
1%
#3620000
b10 #
b10 ,
0%
#3625000
1%
#3630000
b11 #
b11 ,
0%
#3635000
1%
#3640000
b100 #
b100 ,
0%
#3645000
1%
#3650000
b101 #
b101 ,
0%
#3655000
1%
#3660000
b110 #
b110 ,
0%
#3665000
1%
#3670000
b111 #
b111 ,
0%
#3675000
1%
#3680000
b1000 #
b1000 ,
0%
#3685000
1%
#3690000
b1001 #
b1001 ,
0%
#3695000
1%
#3700000
b1010 #
b1010 ,
0%
#3705000
1%
#3710000
b1011 #
b1011 ,
0%
#3715000
1%
#3720000
b1100 #
b1100 ,
0%
#3725000
1%
#3730000
b1101 #
b1101 ,
0%
#3735000
1%
#3740000
b1110 #
b1110 ,
0%
#3745000
1%
#3750000
b1111 #
b1111 ,
0%
#3755000
1%
#3760000
b10000 #
b10000 ,
0%
#3765000
1%
#3770000
b10001 #
b10001 ,
0%
#3775000
1%
#3780000
b10010 #
b10010 ,
0%
#3785000
1%
#3790000
b10011 #
b10011 ,
0%
#3795000
1%
#3800000
b10100 #
b10100 ,
0%
#3805000
1%
#3810000
b10101 #
b10101 ,
0%
#3815000
1%
#3820000
b10110 #
b10110 ,
0%
#3825000
1%
#3830000
b10111 #
b10111 ,
0%
#3835000
1%
#3840000
b11000 #
b11000 ,
0%
#3845000
1%
#3850000
b11001 #
b11001 ,
0%
#3855000
1%
#3860000
b11010 #
b11010 ,
0%
#3865000
1%
#3870000
b11011 #
b11011 ,
0%
#3875000
1%
#3880000
b11100 #
b11100 ,
0%
#3885000
1%
#3890000
b11101 #
b11101 ,
0%
#3895000
1%
#3900000
b11110 #
b11110 ,
0%
1&
#3905000
1%
#3910000
b11111 #
b11111 ,
0%
#3915000
1%
#3920000
b100000 #
b100000 ,
0%
#3925000
1%
#3930000
b100001 #
b100001 ,
0%
#3935000
1%
#3940000
b100010 #
b100010 ,
0%
#3945000
1%
#3950000
b100011 #
b100011 ,
0%
#3955000
1%
#3960000
b100100 #
b100100 ,
0%
#3965000
1%
#3970000
b100101 #
b100101 ,
0%
#3975000
1%
#3980000
b100110 #
b100110 ,
0%
#3985000
1%
#3990000
b100111 #
b100111 ,
0%
#3995000
1%
#4000000
b101000 #
b101000 ,
0%
#4005000
1%
#4010000
b101001 #
b101001 ,
0%
#4015000
1%
#4020000
b101010 #
b101010 ,
0%
#4025000
1%
#4030000
b101011 #
b101011 ,
0%
#4035000
1%
#4040000
b101100 #
b101100 ,
0%
#4045000
1%
#4050000
b101101 #
b101101 ,
0%
#4055000
1%
#4060000
b101110 #
b101110 ,
0%
#4065000
1%
#4070000
b101111 #
b101111 ,
0%
#4075000
1%
#4080000
b110000 #
b110000 ,
0%
#4085000
1%
#4090000
b110001 #
b110001 ,
0%
#4095000
1%
#4100000
b110010 #
b110010 ,
0%
#4105000
1%
#4110000
b110011 #
b110011 ,
0%
#4115000
1%
#4120000
b110100 #
b110100 ,
0%
#4125000
1%
#4130000
b110101 #
b110101 ,
0%
#4135000
1%
#4140000
b110110 #
b110110 ,
0%
#4145000
1%
#4150000
b110111 #
b110111 ,
0%
#4155000
1%
#4160000
b111000 #
b111000 ,
0%
#4165000
1%
#4170000
b111001 #
b111001 ,
0%
#4175000
1%
#4180000
b111010 #
b111010 ,
0%
#4185000
1%
#4190000
b111011 #
b111011 ,
0%
#4195000
1%
#4200000
b0 #
b0 ,
b111 $
b111 +
0%
0&
#4205000
1%
#4210000
b1 #
b1 ,
0%
#4215000
1%
#4220000
b10 #
b10 ,
0%
#4225000
1%
#4230000
b11 #
b11 ,
0%
#4235000
1%
#4240000
b100 #
b100 ,
0%
#4245000
1%
