TIME_COUNTER/time_counter.v
module time_counter(seconds,minutes,hours,reset,clock);
	input wire reset;
	input wire clock;
	
	//Keeping track of the seconds ellapsed (MAX SECONDS = 59)
	output reg [7 : 0] seconds  = 0; 

	//Keeping track of the minutes ellapsed (MAX MINS = 59)
	output reg[7:0]	minutes = 0;

	// Keeping track of the hours ellapsed (MAX HOURS = 99)
	output reg[7:0]	hours = 0;

	//This counter will keep track of the amount of clock pulses
	reg [24:0]counter = 24'b0;		

	//TODO: cambiar linea debajo para adapatar a la FPGA
	//!Atención! se debe cambiar cuando se use en QUARTUS
	// parameter secondReference = 25*(10^6);	//CAMBIAR CUANDO SE PASA A QUARTUS. Amount of clock ticks that represent a SECOND
	parameter secondReference = 250; //!<-- AHI!
	
	//Detection of falling edge in clk_sec singal
	always @(posedge clock)
	begin
		counter += 1;
		//If the counter has reached de second reference we add +1 seconds
		if(counter == secondReference)begin
			counter = 0; // Reset counter
			seconds <= seconds + 1;			//Counts a new second after "secondReference" clock pulses

			if(seconds == 59)  //If seconds limit has been reached, then reset
			begin
				begin
					seconds <= 0;
					minutes <= minutes + 1;
				end
				if(minutes == 59)	//If minutes limit has been reached, then reset and add +1 Hour
					begin
						minutes <= 0;
						hours <= hours + 1;
					end
						if(hours == 99)
							hours <= 0;
			end
		end
	end
endmodule

TIME_COUNTER/clock25M.v
//This clock will model the FPGA's internal clock. 
//`timescale 1ns / 1ns
module clock_gen(output reg clk);

parameter PERIOD = 40;
	 
always
	begin: CLOCK_DRIVER
		clk <= 1'b0;
		#(PERIOD/2);
		clk <= 1'b1;
		#(PERIOD/2);
	end
endmodule

TIME_COUNTER/dut_counters.v
//`timescale 100ns / 100ns 
`timescale 100us / 100us //CLOCK FREQUENCY = 40*timescale--> 40*100us == 1/250 --> se necesitan 250 pulsos para hacer 1 segundo
module hello_world;

  // My signal definitions
  wire clk;
  wire reset;
  wire[7:0]seconds;
  wire[7:0]minutes;
  wire[7:0]hours;

//Modules
  clock_gen clk_gen(clk); 
  time_counter t_counter(seconds,minutes,hours,reset,clk);


  initial begin

    #1000000;
    $finish;

  end

  reg dummy;
  reg[8*64:0] dumpfile_path = "output.vcd";

  initial begin

    //Testing 
    dummy = $value$plusargs("VCD_PATH=%s", dumpfile_path);
    $dumpfile(dumpfile_path);
    $dumpvars(0,hello_world);
    $display("hola");
  end

endmodule // End of Module hello_world

TIME_COUNTER/output.vcd
$date
	Mon Nov 19 17:07:11 2018
$end
$version
	Icarus Verilog
$end
$timescale
	100us
$end
$scope module hello_world $end
$var wire 1 ! reset $end
$var wire 8 " seconds [7:0] $end
$var wire 8 # minutes [7:0] $end
$var wire 8 $ hours [7:0] $end
$var wire 1 % clk $end
$var reg 1 & dummy $end
$var reg 513 ' dumpfile_path [512:0] $end
$scope module clk_gen $end
$var reg 1 % clk $end
$scope begin CLOCK_DRIVER $end
$upscope $end
$upscope $end
$scope module t_counter $end
$var wire 1 % clock $end
$var wire 1 ! reset $end
$var reg 25 ( counter [24:0] $end
$var reg 8 ) hours [7:0] $end
$var reg 8 * minutes [7:0] $end
$var reg 8 + seconds [7:0] $end
$upscope $end
$upscope $end
$enddefinitions $end
#0
$dumpvars
b0 +
b0 *
b0 )
b0 (
b1101111011101010111010001110000011101010111010000101110011101100110001101100100 '
0&
0%
b0 $
b0 #
b0 "
z!
$end
#20
b1 (
1%
#40
0%
#60
b10 (
1%
#80
0%
#100
b11 (
1%
#120
0%
#140
b100 (
1%
#160
0%
#180
b101 (
1%
#200
0%
#220
b110 (
1%
#240
0%
#260
b111 (
1%
#280
0%
#300
b1000 (
1%
#320
0%
#340
b1001 (
1%
#360
0%
#380
b1010 (
1%
#400
0%
#420
b1011 (
1%
#440
0%
#460
b1100 (
1%
#480
0%
#500
b1101 (
1%
#520
0%
#540
b1110 (
1%
#560
0%
#580
b1111 (
1%
#600
0%
#620
b10000 (
1%
#640
0%
#660
b10001 (
1%
#680
0%
#700
b10010 (
1%
#720
0%
#740
b10011 (
1%
#760
0%
#780
b10100 (
1%
#800
0%
#820
b10101 (
1%
#840
0%
#860
b10110 (
1%
#880
0%
#900
b10111 (
1%
#920
0%
#940
b11000 (
1%
#960
0%
#980
b11001 (
1%
#1000
0%
#1020
b11010 (
1%
#1040
0%
#1060
b11011 (
1%
#1080
0%
#1100
b11100 (
1%
#1120
0%
#1140
b11101 (
1%
#1160
0%
#1180
b11110 (
1%
#1200
0%
#1220
b11111 (
1%
#1240
0%
#1260
b100000 (
1%
#1280
0%
#1300
b100001 (
1%
#1320
0%
#1340
b100010 (
1%
#1360
0%
#1380
b100011 (
1%
#1400
0%
#1420
b100100 (
1%
#1440
0%
#1460
b100101 (
1%
#1480
0%
#1500
b100110 (
1%
#1520
0%
#1540
b100111 (
1%
#1560
0%
#1580
b101000 (
1%
#1600
0%
#1620
b101001 (
1%
#1640
0%
#1660
b101010 (
1%
#1680
0%
#1700
b101011 (
1%
#1720
0%
#1740
b101100 (
1%
#1760
0%
#1780
b101101 (
1%
#1800
0%
#1820
b101110 (
1%
#1840
0%
#1860
b101111 (
1%
#1880
0%
#1900
b110000 (
1%
#1920
0%
#1940
b110001 (
1%
#1960
0%
#1980
b110010 (
1%
#2000
0%
#2020
b110011 (
1%
#2040
0%
#2060
b110100 (
1%
#2080
0%
#2100
b110101 (
1%
#2120
0%
#2140
b110110 (
1%
#2160
0%
#2180
b110111 (
1%
#2200
0%
#2220
b111000 (
1%
#2240
0%
#2260
b111001 (
1%
#2280
0%
#2300
b111010 (
1%
#2320
0%
#2340
b111011 (
1%
#2360
0%
#2380
b111100 (
1%
#2400
0%
#2420
b111101 (
1%
#2440
0%
#2460
b111110 (
1%
#2480
0%
#2500
b111111 (
1%
#2520
0%
#2540
b1000000 (
1%
#2560
0%
#2580
b1000001 (
1%
#2600
0%
#2620
b1000010 (
1%
#2640
0%
#2660
b1000011 (
1%
#2680
0%
#2700
b1000100 (
1%
#2720
0%
#2740
b1000101 (
1%
#2760
0%
#2780
b1000110 (
1%
#2800
0%
#2820
b1000111 (
1%
#2840
0%
#2860
b1001000 (
1%
#2880
0%
#2900
b1001001 (
1%
#2920
0%
#2940
b1001010 (
1%
#2960
0%
#2980
b1001011 (
1%
#3000
0%
#3020
b1001100 (
1%
#3040
0%
#3060
b1001101 (
1%
#3080
0%
#3100
b1001110 (
1%
#3120
0%
#3140
b1001111 (
1%
#3160
0%
#3180
b1010000 (
1%
#3200
0%
#3220
b1010001 (
1%
#3240
0%
#3260
b1010010 (
1%
#3280
0%
#3300
b1010011 (
1%
#3320
0%
#3340
b1010100 (
1%
#3360
0%
#3380
b1010101 (
1%
#3400
0%
#3420
b1010110 (
1%
#3440
0%
#3460
b1010111 (
1%
#3480
0%
#3500
b1011000 (
1%
#3520
0%
#3540
b1011001 (
1%
#3560
0%
#3580
b1011010 (
1%
#3600
0%
#3620
b1011011 (
1%
#3640
0%
#3660
b1011100 (
1%
#3680
0%
#3700
b1011101 (
1%
#3720
0%
#3740
b1011110 (
1%
#3760
0%
#3780
b1011111 (
1%
#3800
0%
#3820
b1100000 (
1%
#3840
0%
#3860
b1100001 (
1%
#3880
0%
#3900
b1100010 (
1%
#3920
0%
#3940
b1100011 (
1%
#3960
0%
#3980
b1100100 (
1%
#4000
0%
#4020
b1100101 (
1%
#4040
0%
#4060
b1100110 (
1%
#4080
0%
#4100
b1100111 (
1%
#4120
0%
#4140
b1101000 (
1%
#4160
0%
#4180
b1101001 (
1%
#4200
0%
#4220
b1101010 (
1%
#4240
0%
#4260
b1101011 (
1%
#4280
0%
#4300
b1101100 (
1%
#4320
0%
#4340
b1101101 (
1%
#4360
0%
#4380
b1101110 (
1%
#4400
0%
#4420
b1101111 (
1%
#4440
0%
#4460
b1110000 (
1%
#4480
0%
#4500
b1110001 (
1%
#4520
0%
#4540
b1110010 (
1%
#4560
0%
#4580
b1110011 (
1%
#4600
0%
#4620
b1110100 (
1%
#4640
0%
#4660
b1110101 (
1%
#4680
0%
#4700
b1110110 (
1%
#4720
0%
#4740
b1110111 (
1%
#4760
0%
#4780
b1111000 (
1%
#4800
0%
#4820
b1111001 (
1%
#4840
0%
#4860
b1111010 (
1%
#4880
0%
#4900
b1111011 (
1%
#4920
0%
#4940
b1111100 (
1%
#4960
0%
#4980
b1111101 (
1%
#5000
0%
#5020
b1111110 (
1%
#5040
0%
#5060
b1111111 (
1%
#5080
0%
#5100
b10000000 (
1%
#5120
0%
#5140
b10000001 (
1%
#5160
0%
#5180
b10000010 (
1%
#5200
0%
#5220
b10000011 (
1%
#5240
0%
#5260
b10000100 (
1%
#5280
0%
#5300
b10000101 (
1%
#5320
0%
#5340
b10000110 (
1%
#5360
0%
#5380
b10000111 (
1%
#5400
0%
#5420
b10001000 (
1%
#5440
0%
#5460
b10001001 (
1%
#5480
0%
#5500
b10001010 (
1%
#5520
0%
#5540
b10001011 (
1%
#5560
0%
#5580
b10001100 (
1%
#5600
0%
#5620
b10001101 (
1%
#5640
0%
#5660
b10001110 (
1%
#5680
0%
#5700
b10001111 (
1%
#5720
0%
#5740
b10010000 (
1%
#5760
0%
#5780
b10010001 (
1%
#5800
0%
#5820
b10010010 (
1%
#5840
0%
#5860
b10010011 (
1%
#5880
0%
#5900
b10010100 (
1%
#5920
0%
#5940
b10010101 (
1%
#5960
0%
#5980
b10010110 (
1%
#6000
0%
#6020
b10010111 (
1%
#6040
0%
#6060
b10011000 (
1%
#6080
0%
#6100
b10011001 (
1%
#6120
0%
#6140
b10011010 (
1%
#6160
0%
#6180
b10011011 (
1%
#6200
0%
#6220
b10011100 (
1%
#6240
0%
#6260
b10011101 (
1%
#6280
0%
#6300
b10011110 (
1%
#6320
0%
#6340
b10011111 (
1%
#6360
0%
#6380
b10100000 (
1%
#6400
0%
#6420
b10100001 (
1%
#6440
0%
#6460
b10100010 (
1%
#6480
0%
#6500
b10100011 (
1%
#6520
0%
#6540
b10100100 (
1%
#6560
0%
#6580
b10100101 (
1%
#6600
0%
#6620
b10100110 (
1%
#6640
0%
#6660
b10100111 (
1%
#6680
0%
#6700
b10101000 (
1%
#6720
0%
#6740
b10101001 (
1%
#6760
0%
#6780
b10101010 (
1%
#6800
0%
#6820
b10101011 (
1%
#6840
0%
#6860
b10101100 (
1%
#6880
0%
#6900
b10101101 (
1%
#6920
0%
#6940
b10101110 (
1%
#6960
0%
#6980
b10101111 (
1%
#7000
0%
#7020
b10110000 (
1%
#7040
0%
#7060
b10110001 (
1%
#7080
0%
#7100
b10110010 (
1%
#7120
0%
#7140
b10110011 (
1%
#7160
0%
#7180
b10110100 (
1%
#7200
0%
#7220
b10110101 (
1%
#7240
0%
#7260
b10110110 (
1%
#7280
0%
#7300
b10110111 (
1%
#7320
0%
#7340
b10111000 (
1%
#7360
0%
#7380
b10111001 (
1%
#7400
0%
#7420
b10111010 (
1%
#7440
0%
#7460
b10111011 (
1%
#7480
0%
#7500
b10111100 (
1%
#7520
0%
#7540
b10111101 (
1%
#7560
0%
#7580
b10111110 (
1%
#7600
0%
#7620
b10111111 (
1%
#7640
0%
#7660
b11000000 (
1%
#7680
0%
#7700
b11000001 (
1%
#7720
0%
#7740
b11000010 (
1%
#7760
0%
#7780
b11000011 (
1%
#7800
0%
#7820
b11000100 (
1%
#7840
0%
#7860
b11000101 (
1%
#7880
0%
#7900
b11000110 (
1%
#7920
0%
#7940
b11000111 (
1%
#7960
0%
#7980
b11001000 (
1%
#8000
0%
#8020
b11001001 (
1%
#8040
0%
#8060
b11001010 (
1%
#8080
0%
#8100
b11001011 (
1%
#8120
0%
#8140
b11001100 (
1%
#8160
0%
#8180
b11001101 (
1%
#8200
0%
#8220
b11001110 (
1%
#8240
0%
#8260
b11001111 (
1%
#8280
0%
#8300
b11010000 (
1%
#8320
0%
#8340
b11010001 (
1%
#8360
0%
#8380
b11010010 (
1%
#8400
0%
#8420
b11010011 (
1%
#8440
0%
#8460
b11010100 (
1%
#8480
0%
#8500
b11010101 (
1%
#8520
0%
#8540
b11010110 (
1%
#8560
0%
#8580
b11010111 (
1%
#8600
0%
#8620
b11011000 (
1%
#8640
0%
#8660
b11011001 (
1%
#8680
0%
#8700
b11011010 (
1%
#8720
0%
#8740
b11011011 (
1%
#8760
0%
#8780
b11011100 (
1%
#8800
0%
#8820
b11011101 (
1%
#8840
0%
#8860
b11011110 (
1%
#8880
0%
#8900
b11011111 (
1%
#8920
0%
#8940
b11100000 (
1%
#8960
0%
#8980
b11100001 (
1%
#9000
0%
#9020
b11100010 (
1%
#9040
0%
#9060
b11100011 (
1%
#9080
0%
#9100
b11100100 (
1%
#9120
0%
#9140
b11100101 (
1%
#9160
0%
#9180
b11100110 (
1%
#9200
0%
#9220
b11100111 (
1%
#9240
0%
#9260
b11101000 (
1%
#9280
0%
#9300
b11101001 (
1%
#9320
0%
#9340
b11101010 (
1%
#9360
0%
#9380
b11101011 (
1%
#9400
0%
#9420
b11101100 (
1%
#9440
0%
#9460
b11101101 (
1%
#9480
0%
#9500
b11101110 (
1%
#9520
0%
#9540
b11101111 (
1%
#9560
0%
#9580
b11110000 (
1%
#9600
0%
#9620
b11110001 (
1%
#9640
0%
#9660
b11110010 (
1%
#9680
0%
#9700
b11110011 (
1%
#9720
0%
#9740
b11110100 (
1%
#9760
0%
#9780
b11110101 (
1%
#9800
0%
#9820
b11110110 (
1%
#9840
0%
#9860
b11110111 (
1%
#9880
0%
#9900
b11111000 (
1%
#9920
0%
#9940
b11111001 (
1%
#9960
0%
#9980
b1 "
b1 +
b0 (
1%
#10000
0%
#10020
b1 (
1%
#10040
0%
#10060
b10 (
1%
#10080
0%
#10100
b11 (
1%
#10120
0%
#10140
b100 (
1%
#10160
0%
#10180
b101 (
1%
#10200
0%
#10220
b110 (
1%
#10240
0%
#10260
b111 (
1%
#10280
0%
#10300
b1000 (
1%
#10320
0%
#10340
b1001 (
1%
#10360
0%
#10380
b1010 (
1%
#10400
0%
#10420
b1011 (
1%
#10440
0%
#10460
b1100 (
1%
#10480
0%
#10500
b1101 (
1%
#10520
0%
#10540
b1110 (
1%
#10560
0%
#10580
b1111 (
1%
#10600
0%
#10620
b10000 (
1%
#10640
0%
#10660
b10001 (
1%
#10680
0%
#10700
b10010 (
1%
#10720
0%
#10740
b10011 (
1%
#10760
0%
#10780
b10100 (
1%
#10800
0%
#10820
b10101 (
1%
#10840
0%
#10860
b10110 (
1%
#10880
0%
#10900
b10111 (
1%
#10920
0%
#10940
b11000 (
1%
#10960
0%
#10980
b11001 (
1%
#11000
0%
#11020
b11010 (
1%
#11040
0%
#11060
b11011 (
1%
#11080
0%
#11100
b11100 (
1%
#11120
0%
#11140
b11101 (
1%
#11160
0%
#11180
b11110 (
1%
#11200
0%
#11220
b11111 (
1%
#11240
0%
#11260
b100000 (
1%
#11280
0%
#11300
b100001 (
1%
#11320
0%
#11340
b100010 (
1%
#11360
0%
#11380
b100011 (
1%
#11400
0%
#11420
b100100 (
1%
#11440
0%
#11460
b100101 (
1%
#11480
0%
#11500
b100110 (
1%
#11520
0%
#11540
b100111 (
1%
#11560
0%
#11580
b101000 (
1%
#11600
0%
#11620
b101001 (
1%
#11640
0%
#11660
b101010 (
1%
#11680
0%
#11700
b101011 (
1%
#11720
0%
#11740
b101100 (
1%
#11760
0%
#11780
b101101 (
1%
#11800
0%
#11820
b101110 (
1%
#11840
0%
#11860
b101111 (
1%
#11880
0%
#11900
b110000 (
1%
#11920
0%
#11940
b110001 (
1%
#11960
0%
#11980
b110010 (
1%
#12000
0%
#12020
b110011 (
1%
#12040
0%
#12060
b110100 (
1%
#12080
0%
#12100
b110101 (
1%
#12120
0%
#12140
b110110 (
1%
#12160
0%
#12180
b110111 (
1%
#12200
0%
#12220
b111000 (
1%
#12240
0%
#12260
b111001 (
1%
#12280
0%
#12300
b111010 (
1%
#12320
0%
#12340
b111011 (
1%
#12360
0%
#12380
b111100 (
1%
#12400
0%
#12420
b111101 (
1%
#12440
0%
#12460
b111110 (
1%
#12480
0%
#12500
b111111 (
1%
#12520
0%
#12540
b1000000 (
1%
#12560
0%
#12580
b1000001 (
1%
#12600
0%
#12620
b1000010 (
1%
#12640
0%
#12660
b1000011 (
1%
#12680
0%
#12700
b1000100 (
1%
#12720
0%
#12740
b1000101 (
1%
#12760
0%
#12780
b1000110 (
1%
#12800
0%
#12820
b1000111 (
1%
#12840
0%
#12860
b1001000 (
1%
#12880
0%
#12900
b1001001 (
1%
#12920
0%
#12940
b1001010 (
1%
#12960
0%
#12980
b1001011 (
1%
#13000
0%
#13020
b1001100 (
1%
#13040
0%
#13060
b1001101 (
1%
#13080
0%
#13100
b1001110 (
1%
#13120
0%
#13140
b1001111 (
1%
#13160
0%
#13180
b1010000 (
1%
#13200
0%
#13220
b1010001 (
1%
#13240
0%
#13260
b1010010 (
1%
#13280
0%
#13300
b1010011 (
1%
#13320
0%
#13340
b1010100 (
1%
#13360
0%
#13380
b1010101 (
1%
#13400
0%
#13420
b1010110 (
1%
#13440
0%
#13460
b1010111 (
1%
#13480
0%
#13500
b1011000 (
1%
#13520
0%
#13540
b1011001 (
1%
#13560
0%
#13580
b1011010 (
1%
#13600
0%
#13620
b1011011 (
1%
#13640
0%
#13660
b1011100 (
1%
#13680
0%
#13700
b1011101 (
1%
#13720
0%
#13740
b1011110 (
1%
#13760
0%
#13780
b1011111 (
1%
#13800
0%
#13820
b1100000 (
1%
#13840
0%
#13860
b1100001 (
1%
#13880
0%
#13900
b1100010 (
1%
#13920
0%
#13940
b1100011 (
1%
#13960
0%
#13980
b1100100 (
1%
#14000
0%
#14020
b1100101 (
1%
#14040
0%
#14060
b1100110 (
1%
#14080
0%
#14100
b1100111 (
1%
#14120
0%
#14140
b1101000 (
1%
#14160
0%
#14180
b1101001 (
1%
#14200
0%
#14220
b1101010 (
1%
#14240
0%
#14260
b1101011 (
1%
#14280
0%
#14300
b1101100 (
1%
#14320
0%
#14340
b1101101 (
1%
#14360
0%
#14380
b1101110 (
1%
#14400
0%
#14420
b1101111 (
1%
#14440
0%
#14460
b1110000 (
1%
#14480
0%
#14500
b1110001 (
1%
#14520
0%
#14540
b1110010 (
1%
#14560
0%
#14580
b1110011 (
1%
#14600
0%
#14620
b1110100 (
1%
#14640
0%
#14660
b1110101 (
1%
#14680
0%
#14700
b1110110 (
1%
#14720
0%
#14740
b1110111 (
1%
#14760
0%
#14780
b1111000 (
1%
#14800
0%
#14820
b1111001 (
1%
#14840
0%
#14860
b1111010 (
1%
#14880
0%
#14900
b1111011 (
1%
#14920
0%
#14940
b1111100 (
1%
#14960
0%
#14980
b1111101 (
1%
#15000
0%
#15020
b1111110 (
1%
#15040
0%
#15060
b1111111 (
1%
#15080
0%
#15100
b10000000 (
1%
#15120
0%
#15140
b10000001 (
1%
#15160
0%
#15180
b10000010 (
1%
#15200
0%
#15220
b10000011 (
1%
#15240
0%
#15260
b10000100 (
1%
#15280
0%
#15300
b10000101 (
1%
#15320
0%
#15340
b10000110 (
1%
#15360
0%
#15380
b10000111 (
1%
#15400
0%
#15420
b10001000 (
1%
#15440
0%
#15460
b10001001 (
1%
#15480
0%
#15500
b10001010 (
1%
#15520
0%
#15540
b10001011 (
1%
#15560
0%
#15580
b10001100 (
1%
#15600
0%
#15620
b10001101 (
1%
#15640
0%
#15660
b10001110 (
1%
#15680
0%
#15700
b10001111 (
1%
#15720
0%
#15740
b10010000 (
1%
#15760
0%
#15780
b10010001 (
1%
#15800
0%
#15820
b10010010 (
1%
#15840
0%
#15860
b10010011 (
1%
#15880
0%
#15900
b10010100 (
1%
#15920
0%
#15940
b10010101 (
1%
#15960
0%
#15980
b10010110 (
1%
#16000
0%
#16020
b10010111 (
1%
#16040
0%
#16060
b10011000 (
1%
#16080
0%
#16100
b10011001 (
1%
#16120
0%
#16140
b10011010 (
1%
#16160
0%
#16180
b10011011 (
1%
#16200
0%
#16220
b10011100 (
1%
#16240
0%
#16260
b10011101 (
1%
#16280
0%
#16300
b10011110 (
1%
#16320
0%
#16340
b10011111 (
1%
#16360
0%
#16380
b10100000 (
1%
#16400
0%
#16420
b10100001 (
1%
#16440
0%
#16460
b10100010 (
1%
#16480
0%
#16500
b10100011 (
1%
#16520
0%
#16540
b10100100 (
1%
#16560
0%
#16580
b10100101 (
1%
#16600
0%
#16620
b10100110 (
1%
#16640
0%
#16660
b10100111 (
1%
#16680
0%
#16700
b10101000 (
1%
#16720
0%
#16740
b10101001 (
1%
#16760
0%
#16780
b10101010 (
1%
#16800
0%
#16820
b10101011 (
1%
#16840
0%
#16860
b10101100 (
1%
#16880
0%
#16900
b10101101 (
1%
#16920
0%
#16940
b10101110 (
1%
#16960
0%
#16980
b10101111 (
1%
#17000
0%
#17020
b10110000 (
1%
#17040
0%
#17060
b10110001 (
1%
#17080
0%
#17100
b10110010 (
1%
#17120
0%
#17140
b10110011 (
1%
#17160
0%
#17180
b10110100 (
1%
#17200
0%
#17220
b10110101 (
1%
#17240
0%
#17260
b10110110 (
1%
#17280
0%
#17300
b10110111 (
1%
#17320
0%
#17340
b10111000 (
1%
#17360
0%
#17380
b10111001 (
1%
#17400
0%
#17420
b10111010 (
1%
#17440
0%
#17460
b10111011 (
1%
#17480
0%
#17500
b10111100 (
1%
#17520
0%
#17540
b10111101 (
1%
#17560
0%
#17580
b10111110 (
1%
#17600
0%
#17620
b10111111 (
1%
#17640
0%
#17660
b11000000 (
1%
#17680
0%
#17700
b11000001 (
1%
#17720
0%
#17740
b11000010 (
1%
#17760
0%
#17780
b11000011 (
1%
#17800
0%
#17820
b11000100 (
1%
#17840
0%
#17860
b11000101 (
1%
#17880
0%
#17900
b11000110 (
1%
#17920
0%
#17940
b11000111 (
1%
#17960
0%
#17980
b11001000 (
1%
#18000
0%
#18020
b11001001 (
1%
#18040
0%
#18060
b11001010 (
1%
#18080
0%
#18100
b11001011 (
1%
#18120
0%
#18140
b11001100 (
1%
#18160
0%
#18180
b11001101 (
1%
#18200
0%
#18220
b11001110 (
1%
#18240
0%
#18260
b11001111 (
1%
#18280
0%
#18300
b11010000 (
1%
#18320
0%
#18340
b11010001 (
1%
#18360
0%
#18380
b11010010 (
1%
#18400
0%
#18420
b11010011 (
1%
#18440
0%
#18460
b11010100 (
1%
#18480
0%
#18500
b11010101 (
1%
#18520
0%
#18540
b11010110 (
1%
#18560
0%
#18580
b11010111 (
1%
#18600
0%
#18620
b11011000 (
1%
#18640
0%
#18660
b11011001 (
1%
#18680
0%
#18700
b11011010 (
1%
#18720
0%
#18740
b11011011 (
1%
#18760
0%
#18780
b11011100 (
1%
#18800
0%
#18820
b11011101 (
1%
#18840
0%
#18860
b11011110 (
1%
#18880
0%
#18900
b11011111 (
1%
#18920
0%
#18940
b11100000 (
1%
#18960
0%
#18980
b11100001 (
1%
#19000
0%
#19020
b11100010 (
1%
#19040
0%
#19060
b11100011 (
1%
#19080
0%
#19100
b11100100 (
1%
#19120
0%
#19140
b11100101 (
1%
#19160
0%
#19180
b11100110 (
1%
#19200
0%
#19220
b11100111 (
1%
#19240
0%
#19260
b11101000 (
1%
#19280
0%
#19300
b11101001 (
1%
#19320
0%
#19340
b11101010 (
1%
#19360
0%
#19380
b11101011 (
1%
#19400
0%
#19420
b11101100 (
1%
#19440
0%
#19460
b11101101 (
1%
#19480
0%
#19500
b11101110 (
1%
#19520
0%
#19540
b11101111 (
1%
#19560
0%
#19580
b11110000 (
1%
#19600
0%
#19620
b11110001 (
1%
#19640
0%
#19660
b11110010 (
1%
#19680
0%
#19700
b11110011 (
1%
#19720
0%
#19740
b11110100 (
1%
#19760
0%
#19780
b11110101 (
1%
#19800
0%
#19820
b11110110 (
1%
#19840
0%
#19860
b11110111 (
1%
#19880
0%
#19900
b11111000 (
1%
#19920
0%
#19940
b11111001 (
1%
#19960
0%
#19980
b10 "
b10 +
b0 (
1%
#20000
0%
#20020
b1 (
1%
#20040
0%
#20060
b10 (
1%
#20080
0%
#20100
b11 (
1%
#20120
0%
#20140
b100 (
1%
#20160
0%
#20180
b101 (
1%
#20200
0%
#20220
b110 (
1%
#20240
0%
#20260
b111 (
1%
#20280
0%
#20300
b1000 (
1%
#20320
0%
#20340
b1001 (
1%
#20360
0%
#20380
b1010 (
1%
#20400
0%
#20420
b1011 (
1%
#20440
0%
#20460
b1100 (
1%
#20480
0%
#20500
b1101 (
1%
#20520
0%
#20540
b1110 (
1%
#20560
0%
#20580
b1111 (
1%
#20600
0%
#20620
b10000 (
1%
#20640
0%
#20660
b10001 (
1%
#20680
0%
#20700
b10010 (
1%
#20720
0%
#20740
b10011 (
1%
#20760
0%
#20780
b10100 (
1%
#20800
0%
#20820
b10101 (
1%
#20840
0%
#20860
b10110 (
1%
#20880
0%
#20900
b10111 (
1%
#20920
0%
#20940
b11000 (
1%
#20960
0%
#20980
b11001 (
1%
#21000
0%
#21020
b11010 (
1%
#21040
0%
#21060
b11011 (
1%
#21080
0%
#21100
b11100 (
1%
#21120
0%
#21140
b11101 (
1%
#21160
0%
#21180
b11110 (
1%
#21200
0%
#21220
b11111 (
1%
#21240
0%
#21260
b100000 (
1%
#21280
0%
#21300
b100001 (
1%
#21320
0%
#21340
b100010 (
1%
#21360
0%
#21380
b100011 (
1%
#21400
0%
#21420
b100100 (
1%
#21440
0%
#21460
b100101 (
1%
#21480
0%
#21500
b100110 (
1%
#21520
0%
#21540
b100111 (
1%
#21560
0%
#21580
b101000 (
1%
#21600
0%
#21620
b101001 (
1%
#21640
0%
#21660
b101010 (
1%
#21680
0%
#21700
b101011 (
1%
#21720
0%
#21740
b101100 (
1%
#21760
0%
#21780
b101101 (
1%
#21800
0%
#21820
b101110 (
1%
#21840
0%
#21860
b101111 (
1%
#21880
0%
#21900
b110000 (
1%
#21920
0%
#21940
b110001 (
1%
#21960
0%
#21980
b110010 (
1%
#22000
0%
#22020
b110011 (
1%
#22040
0%
#22060
b110100 (
1%
#22080
0%
#22100
b110101 (
1%
#22120
0%
#22140
b110110 (
1%
#22160
0%
#22180
b110111 (
1%
#22200
0%
#22220
b111000 (
1%
#22240
0%
#22260
b111001 (
1%
#22280
0%
#22300
b111010 (
1%
#22320
0%
#22340
b111011 (
1%
#22360
0%
#22380
b111100 (
1%
#22400
0%
#22420
b111101 (
1%
#22440
0%
#22460
b111110 (
1%
#22480
0%
#22500
b111111 (
1%
#22520
0%
#22540
b1000000 (
1%
#22560
0%
#22580
b1000001 (
1%
#22600
0%
#22620
b1000010 (
1%
#22640
0%
#22660
b1000011 (
1%
#22680
0%
#22700
b1000100 (
1%
#22720
0%
#22740
b1000101 (
1%
#22760
0%
#22780
b1000110 (
1%
#22800
0%
#22820
b1000111 (
1%
#22840
0%
#22860
b1001000 (
1%
#22880
0%
#22900
b1001001 (
1%
#22920
0%
#22940
b1001010 (
1%
#22960
0%
#22980
b1001011 (
1%
#23000
0%
#23020
b1001100 (
1%
#23040
0%
#23060
b1001101 (
1%
#23080
0%
#23100
b1001110 (
1%
#23120
0%
#23140
b1001111 (
1%
#23160
0%
#23180
b1010000 (
1%
#23200
0%
#23220
b1010001 (
1%
#23240
0%
#23260
b1010010 (
1%
#23280
0%
#23300
b1010011 (
1%
#23320
0%
#23340
b1010100 (
1%
#23360
0%
#23380
b1010101 (
1%
#23400
0%
#23420
b1010110 (
1%
#23440
0%
#23460
b1010111 (
1%
#23480
0%
#23500
b1011000 (
1%
#23520
0%
#23540
b1011001 (
1%
#23560
0%
#23580
b1011010 (
1%
#23600
0%
#23620
b1011011 (
1%
#23640
0%
#23660
b1011100 (
1%
#23680
0%
#23700
b1011101 (
1%
#23720
0%
#23740
b1011110 (
1%
#23760
0%
#23780
b1011111 (
1%
#23800
0%
#23820
b1100000 (
1%
#23840
0%
#23860
b1100001 (
1%
#23880
0%
#23900
b1100010 (
1%
#23920
0%
#23940
b1100011 (
1%
#23960
0%
#23980
b1100100 (
1%
#24000
0%
#24020
b1100101 (
1%
#24040
0%
#24060
b1100110 (
1%
#24080
0%
#24100
b1100111 (
1%
#24120
0%
#24140
b1101000 (
1%
#24160
0%
#24180
b1101001 (
1%
#24200
0%
#24220
b1101010 (
1%
#24240
0%
#24260
b1101011 (
1%
#24280
0%
#24300
b1101100 (
1%
#24320
0%
#24340
b1101101 (
1%
#24360
0%
#24380
b1101110 (
1%
#24400
0%
#24420
b1101111 (
1%
#24440
0%
#24460
b1110000 (
1%
#24480
0%
#24500
b1110001 (
1%
#24520
0%
#24540
b1110010 (
1%
#24560
0%
#24580
b1110011 (
1%
#24600
0%
#24620
b1110100 (
1%
#24640
0%
#24660
b1110101 (
1%
#24680
0%
#24700
b1110110 (
1%
#24720
0%
#24740
b1110111 (
1%
#24760
0%
#24780
b1111000 (
1%
#24800
0%
#24820
b1111001 (
1%
#24840
0%
#24860
b1111010 (
1%
#24880
0%
#24900
b1111011 (
1%
#24920
0%
#24940
b1111100 (
1%
#24960
0%
#24980
b1111101 (
1%
#25000
0%
#25020
b1111110 (
1%
#25040
0%
#25060
b1111111 (
1%
#25080
0%
#25100
b10000000 (
1%
#25120
0%
#25140
b10000001 (
1%
#25160
0%
#25180
b10000010 (
1%
#25200
0%
#25220
b10000011 (
1%
#25240
0%
#25260
b10000100 (
1%
#25280
0%
#25300
b10000101 (
1%
#25320
0%
#25340
b10000110 (
1%
#25360
0%
#25380
b10000111 (
1%
#25400
0%
#25420
b10001000 (
1%
#25440
0%
#25460
b10001001 (
1%
#25480
0%
#25500
b10001010 (
1%
#25520
0%
#25540
b10001011 (
1%
#25560
0%
#25580
b10001100 (
1%
#25600
0%
#25620
b10001101 (
1%
#25640
0%
#25660
b10001110 (
1%
#25680
0%
#25700
b10001111 (
1%
#25720
0%
#25740
b10010000 (
1%
#25760
0%
#25780
b10010001 (
1%
#25800
0%
